heap/__init__.py
heap/heap.py
heap/node.py
heap_tree-0.1.0.dist-info/METADATA
heap_tree-0.1.0.dist-info/WHEEL
heap_tree-0.1.0.dist-info/top_level.txt
heap_tree-0.1.0.dist-info/RECORD
